LICENSE
README.md
setup.cfg
setup.py
mouth/__init__.py
mouth/__main__.py
mouth/errors.py
mouth/records.py
mouth/definitions/locale.json
mouth/definitions/template.json
mouth/definitions/template_email.json
mouth/definitions/template_sms.json
mouth_oc.egg-info/PKG-INFO
mouth_oc.egg-info/SOURCES.txt
mouth_oc.egg-info/dependency_links.txt
mouth_oc.egg-info/entry_points.txt
mouth_oc.egg-info/requires.txt
mouth_oc.egg-info/top_level.txt
mouth_oc.egg-info/zip-safe