Metadata-Version: 2.1
Name: mouth-oc
Version: 1.0.6
Summary: Mouth contains a service to run outgoing communications like email and sms messages
Home-page: https://ouroboroscoding.com/body/mouth
Author: Chris Nasr - Ouroboros Coding Inc.
Author-email: chris@ouroboroscoding.com
License: Custom
Project-URL: Documentation, https://ouroboroscoding.com/body/mouth
Project-URL: Source, https://github.com/ouroboroscoding/mouth
Project-URL: Tracker, https://github.com/ouroboroscoding/mouth/issues
Keywords: rest,microservices
Platform: UNKNOWN
Requires-Python: >=3.10
License-File: LICENSE
